apropos/__init__.py
apropos/goldminer/__init__.py
apropos/goldminer/output/__init__.py
apropos/goldminer/output/goldQt.py
apropos/goldminer/reports/__init__.py
apropos/goldminer/reports/cancel.svg
apropos/goldminer/reports/check.svg
apropos/goldminer/reports/hardhat.svg
apropos/goldminer/reports/header.html
apropos/goldminer/reports/navbar-summary.html
apropos/goldminer/reports/navbar.html
apropos/goldminer/reports/report.css
apropos/goldminer/reports/summary-template.md
apropos/goldminer/reports/template.html
apropos/goldminer/reports/template.md
apropos/goldminer/tools/__init__.py
apropos/goldminer/tools/auditor.py
apropos/goldminer/tools/fingerprinter.py
apropos/goldminer/tools/tande.py
gold_miner_ui-1.5.dist-info/LICENSE
gold_miner_ui-1.5.dist-info/METADATA
gold_miner_ui-1.5.dist-info/WHEEL
gold_miner_ui-1.5.dist-info/entry_points.txt
gold_miner_ui-1.5.dist-info/top_level.txt
gold_miner_ui-1.5.dist-info/RECORD
