Metadata-Version: 2.1
Name: gold-miner-ui
Version: 1.5
Summary: A UI plugin that adds graphical extensions to gold-miner
Home-page: https://gitlab.com/isi-apropos/gold-miner-ui
Author: Wes Hardaker
Author-email: opensource@hardakers.net
Classifier: Programming Language :: Python :: 3
Classifier: Operating System :: OS Independent
Requires-Python: >=3.6
License-File: LICENSE
Requires-Dist: gold-miner
Requires-Dist: PyQt5
Requires-Dist: pyqtgraph
Requires-Dist: matplotlib
Requires-Dist: multikeygraph
Requires-Dist: jinja2
Requires-Dist: roc-utils
Requires-Dist: pyaml
